ezlogger
