Metadata-Version: 1.1
Name: ezlogger
Version: 1.0.2
Summary: ezlogger - The purpose of this module is to provide python scripters a very easy logging wrapper to handle more difficult to setup functions.
Home-page: https://github.com/zerosignal0/ezlogger/blob/master/README.md
Author: Gary Wright
Author-email: zerosignal0@msn.com
License: Apache2
Platform: UNKNOWN
Classifier: Intended Audience :: Developers
Classifier: Programming Language :: Python :: 3.4
Classifier: Programming Language :: Python :: 3.3
Classifier: Programming Language :: Python :: 3.2
Classifier: Programming Language :: Python :: 2.7
Classifier: Programming Language :: Python
